pydasher/__init__.py
pydasher/base.py
pydasher/datatypes.py
pydasher/import_module.py
pydasher/py.typed
pydasher/serialization.py
pydasher-0.1.0.dist-info/LICENSE
pydasher-0.1.0.dist-info/WHEEL
pydasher-0.1.0.dist-info/METADATA
pydasher-0.1.0.dist-info/RECORD
